nnreport/.DS_Store
nnreport/BeautifulReport.py
nnreport/LICENSE
nnreport/README.md
nnreport/__init__.py
nnreport/template/template
nnreport/tests/test_make_report.py
nnreport-1.0.3.dist-info/DESCRIPTION.rst
nnreport-1.0.3.dist-info/METADATA
nnreport-1.0.3.dist-info/RECORD
nnreport-1.0.3.dist-info/WHEEL
nnreport-1.0.3.dist-info/metadata.json
nnreport-1.0.3.dist-info/top_level.txt
nnreport-1.0.3.dist-info/zip-safe
